preflights/__init__.py
preflights/adapters/__init__.py
preflights/adapters/anthropic_llm.py
preflights/adapters/context_builder.py
preflights/adapters/default_config.py
preflights/adapters/file_session.py
preflights/adapters/filesystem.py
preflights/adapters/fixed_clock.py
preflights/adapters/in_memory_session.py
preflights/adapters/isolated_filesystem.py
preflights/adapters/llm_base.py
preflights/adapters/llm_debug.py
preflights/adapters/llm_errors.py
preflights/adapters/llm_factory.py
preflights/adapters/llm_prompts.py
preflights/adapters/llm_validation.py
preflights/adapters/mock_llm.py
preflights/adapters/openai_llm.py
preflights/adapters/openrouter_llm.py
preflights/adapters/random_uid.py
preflights/adapters/sequential_uid.py
preflights/adapters/simple_file_context.py
preflights/adapters/system_clock.py
preflights/application/__init__.py
preflights/application/extraction_config.py
preflights/application/llm_config.py
preflights/application/preflights_app.py
preflights/application/prompt_builder.py
preflights/application/question_filter.py
preflights/application/types.py
preflights/application/ports/__init__.py
preflights/application/ports/clock.py
preflights/application/ports/config.py
preflights/application/ports/file_context.py
preflights/application/ports/filesystem.py
preflights/application/ports/llm.py
preflights/application/ports/session.py
preflights/application/ports/uid.py
preflights/cli/__init__.py
preflights/cli/errors.py
preflights/cli/main.py
preflights/cli/output.py
preflights/cli/prompts.py
preflights/cli/repo.py
preflights/cli/state.py
preflights/cli/validation.py
preflights/core/__init__.py
preflights/core/adr_builder.py
preflights/core/clarifier.py
preflights/core/decision_detector.py
preflights/core/intent_extractor.py
preflights/core/process.py
preflights/core/snapshot_builder.py
preflights/core/task_builder.py
preflights/core/types.py
preflights/core/validators.py
preflights/mcp/__init__.py
preflights/mcp/server.py
preflights/mcp/tools.py
preflights-1.1.4.dist-info/METADATA
preflights-1.1.4.dist-info/WHEEL
preflights-1.1.4.dist-info/entry_points.txt
preflights-1.1.4.dist-info/licenses/LICENSE
preflights-1.1.4.dist-info/RECORD
