Metadata-Version: 2.4
Name: preflights
Version: 1.1.4
Summary: Clarify decisions before AI-assisted coding
Author: Preflights Team
License: Apache-2.0
License-File: LICENSE
Requires-Python: >=3.11
Requires-Dist: click>=8.1
Requires-Dist: mcp>=1.0.0
Provides-Extra: anthropic
Requires-Dist: anthropic>=0.40.0; extra == 'anthropic'
Provides-Extra: dev
Requires-Dist: hypothesis>=6.0; extra == 'dev'
Requires-Dist: mypy>=1.7; extra == 'dev'
Requires-Dist: pytest-asyncio>=0.23; extra == 'dev'
Requires-Dist: pytest-cov>=4.1; extra == 'dev'
Requires-Dist: pytest>=7.4; extra == 'dev'
Requires-Dist: ruff>=0.1; extra == 'dev'
Provides-Extra: llm
Requires-Dist: anthropic>=0.40.0; extra == 'llm'
Requires-Dist: openai>=1.50.0; extra == 'llm'
Provides-Extra: openai
Requires-Dist: openai>=1.50.0; extra == 'openai'
